main.py
mc3000_backup.py
mc3000_config.py
mc3000_graphs.py
mc3000_gui.py
mc3000_profiles.py
mc3000_protocol.py
mc3000_usb.py
skyrc_mc3000_gui-1.6.0.dist-info/licenses/LICENSE
skyrc_mc3000_gui-1.6.0.dist-info/METADATA
skyrc_mc3000_gui-1.6.0.dist-info/WHEEL
skyrc_mc3000_gui-1.6.0.dist-info/entry_points.txt
skyrc_mc3000_gui-1.6.0.dist-info/top_level.txt
skyrc_mc3000_gui-1.6.0.dist-info/RECORD
