Metadata-Version: 2.4
Name: skyrc-mc3000-gui
Version: 1.6.0
Summary: Cross-platform GUI for SKYRC MC3000 battery charger
Author-email: Denys Fedoryshchenko <denys.f@collabora.com>
License: MIT License
Project-URL: Homepage, https://github.com/nuclearcat/SkyRCMC3000-GUI
Project-URL: Repository, https://github.com/nuclearcat/SkyRCMC3000-GUI
Project-URL: Documentation, https://github.com/nuclearcat/SkyRCMC3000-GUI/tree/main/docs
Project-URL: Bug Tracker, https://github.com/nuclearcat/SkyRCMC3000-GUI/issues
Keywords: skyrc,mc3000,battery,charger,gui,usb,hid
Classifier: Development Status :: 4 - Beta
Classifier: Environment :: X11 Applications :: Qt
Classifier: Intended Audience :: End Users/Desktop
Classifier: License :: OSI Approved :: MIT License
Classifier: Operating System :: OS Independent
Classifier: Operating System :: Microsoft :: Windows
Classifier: Operating System :: POSIX :: Linux
Classifier: Operating System :: MacOS
Classifier: Programming Language :: Python :: 3
Classifier: Programming Language :: Python :: 3.8
Classifier: Programming Language :: Python :: 3.9
Classifier: Programming Language :: Python :: 3.10
Classifier: Programming Language :: Python :: 3.11
Classifier: Programming Language :: Python :: 3.12
Classifier: Programming Language :: Python :: 3.13
Classifier: Topic :: Scientific/Engineering
Classifier: Topic :: Utilities
Requires-Python: >=3.8
License-File: LICENSE
Requires-Dist: PySide6>=6.5.0
Requires-Dist: hid>=1.0.5
Requires-Dist: pyqtgraph>=0.13.0
Requires-Dist: numpy>=1.20.0
Provides-Extra: dev
Requires-Dist: pytest; extra == "dev"
Requires-Dist: black; extra == "dev"
Requires-Dist: mypy; extra == "dev"
Dynamic: license-file
